{
  "minecraft:recipes/decorations/light_blue_bed_from_white_bed": {
    "criteria": {
      "has_bed": "2021-12-23 05:13:47 +0000"
    },
    "done": true
  },
  "minecraft:recipes/building_blocks/brick_stairs_from_bricks_stonecutting": {
    "criteria": {
      "has_bricks": "2021-12-22 01:14:20 +0000"
    },
    "done": true
  },
  "minecraft:recipes/redstone/tnt": {
    "criteria": {
      "has_gunpowder": "2021-12-23 05:27:26 +0000"
    },
    "done": true
  },
  "minecraft:recipes/tools/wooden_axe": {
    "criteria": {
      "has_stick": "2021-12-23 05:14:32 +0000"
    },
    "done": true
  },
  "minecraft:recipes/decorations/spruce_sign": {
    "criteria": {
      "has_planks": "2021-12-22 01:12:36 +0000"
    },
    "done": true
  },
  "minecraft:adventure/kill_a_mob": {
    "criteria": {
      "minecraft:zombie": "2021-12-19 23:20:18 +0000"
    },
    "done": true
  },
  "minecraft:recipes/decorations/magenta_bed_from_white_bed": {
    "criteria": {
      "has_bed": "2021-12-23 05:13:47 +0000"
    },
    "done": true
  },
  "minecraft:recipes/decorations/brick_wall": {
    "criteria": {
      "has_bricks": "2021-12-22 01:14:20 +0000"
    },
    "done": true
  },
  "minecraft:recipes/decorations/orange_bed_from_white_bed": {
    "criteria": {
      "has_bed": "2021-12-23 05:13:47 +0000"
    },
    "done": true
  },
  "minecraft:recipes/building_blocks/brick_stairs": {
    "criteria": {
      "has_bricks": "2021-12-22 01:14:20 +0000"
    },
    "done": true
  },
  "minecraft:recipes/redstone/spruce_door": {
    "criteria": {
      "has_planks": "2021-12-22 01:12:36 +0000"
    },
    "done": true
  },
  "minecraft:recipes/misc/wheat": {
    "criteria": {
      "has_hay_block": "2021-12-22 01:14:33 +0000"
    },
    "done": true
  },
  "minecraft:recipes/food/cooked_salmon_from_smoking": {
    "criteria": {
      "has_salmon": "2021-12-19 23:17:28 +0000"
    },
    "done": true
  },
  "minecraft:husbandry/make_a_sign_glow": {
    "criteria": {
      "make_a_sign_glow": "2021-12-22 01:15:58 +0000"
    },
    "done": true
  },
  "minecraft:recipes/redstone/target": {
    "criteria": {
      "has_hay_block": "2021-12-22 01:14:33 +0000"
    },
    "done": true
  },
  "minecraft:recipes/misc/yellow_dye_from_sunflower": {
    "criteria": {
      "has_sunflower": "2021-12-19 23:15:21 +0000"
    },
    "done": true
  },
  "minecraft:recipes/redstone/spruce_fence_gate": {
    "criteria": {
      "has_planks": "2021-12-22 01:12:36 +0000"
    },
    "done": true
  },
  "minecraft:adventure/adventuring_time": {
    "criteria": {
      "minecraft:sunflower_plains": "2021-12-19 23:12:12 +0000",
      "minecraft:beach": "2021-12-19 23:21:20 +0000",
      "minecraft:river": "2021-12-19 23:17:09 +0000",
      "minecraft:forest": "2021-12-23 05:32:14 +0000",
      "minecraft:flower_forest": "2021-12-23 05:11:13 +0000",
      "minecraft:plains": "2021-12-22 00:48:09 +0000"
    },
    "done": false
  },
  "minecraft:recipes/misc/charcoal": {
    "criteria": {
      "has_log": "2021-12-19 23:15:43 +0000"
    },
    "done": true
  },
  "minecraft:recipes/decorations/crafting_table": {
    "criteria": {
      "has_planks": "2021-12-22 01:12:36 +0000"
    },
    "done": true
  },
  "minecraft:recipes/decorations/purple_bed_from_white_bed": {
    "criteria": {
      "has_bed": "2021-12-23 05:13:47 +0000"
    },
    "done": true
  },
  "minecraft:adventure/sleep_in_bed": {
    "criteria": {
      "slept_in_bed": "2021-12-23 05:13:49 +0000"
    },
    "done": true
  },
  "minecraft:recipes/decorations/campfire": {
    "criteria": {
      "has_stick": "2021-12-23 05:14:32 +0000"
    },
    "done": true
  },
  "minecraft:recipes/tools/wooden_pickaxe": {
    "criteria": {
      "has_stick": "2021-12-23 05:14:32 +0000"
    },
    "done": true
  },
  "minecraft:husbandry/root": {
    "criteria": {
      "consumed_item": "2021-12-19 23:17:30 +0000"
    },
    "done": true
  },
  "minecraft:recipes/decorations/ladder": {
    "criteria": {
      "has_stick": "2021-12-23 05:14:32 +0000"
    },
    "done": true
  },
  "minecraft:recipes/transportation/birch_boat": {
    "criteria": {
      "in_water": "2021-12-19 23:15:17 +0000"
    },
    "done": true
  },
  "minecraft:recipes/decorations/black_bed_from_white_bed": {
    "criteria": {
      "has_bed": "2021-12-23 05:13:47 +0000"
    },
    "done": true
  },
  "minecraft:recipes/redstone/spruce_button": {
    "criteria": {
      "has_planks": "2021-12-22 01:12:36 +0000"
    },
    "done": true
  },
  "minecraft:recipes/decorations/barrel": {
    "criteria": {
      "has_planks": "2021-12-22 01:12:36 +0000"
    },
    "done": true
  },
  "minecraft:recipes/tools/wooden_shovel": {
    "criteria": {
      "has_stick": "2021-12-23 05:14:32 +0000"
    },
    "done": true
  },
  "minecraft:recipes/transportation/acacia_boat": {
    "criteria": {
      "in_water": "2021-12-19 23:15:17 +0000"
    },
    "done": true
  },
  "minecraft:recipes/misc/white_dye": {
    "criteria": {
      "has_bone_meal": "2021-12-23 05:13:16 +0000"
    },
    "done": true
  },
  "minecraft:recipes/misc/stick": {
    "criteria": {
      "has_planks": "2021-12-22 01:12:36 +0000"
    },
    "done": true
  },
  "minecraft:recipes/decorations/cyan_bed_from_white_bed": {
    "criteria": {
      "has_bed": "2021-12-23 05:13:47 +0000"
    },
    "done": true
  },
  "minecraft:adventure/root": {
    "criteria": {
      "killed_something": "2021-12-19 23:17:27 +0000"
    },
    "done": true
  },
  "minecraft:husbandry/plant_seed": {
    "criteria": {
      "wheat": "2021-12-23 05:18:24 +0000"
    },
    "done": true
  },
  "minecraft:recipes/transportation/jungle_boat": {
    "criteria": {
      "in_water": "2021-12-19 23:15:17 +0000"
    },
    "done": true
  },
  "minecraft:recipes/transportation/spruce_boat": {
    "criteria": {
      "in_water": "2021-12-19 23:15:17 +0000"
    },
    "done": true
  },
  "minecraft:recipes/food/cooked_salmon_from_campfire_cooking": {
    "criteria": {
      "has_salmon": "2021-12-19 23:17:28 +0000"
    },
    "done": true
  },
  "minecraft:recipes/decorations/gray_bed_from_white_bed": {
    "criteria": {
      "has_bed": "2021-12-23 05:13:47 +0000"
    },
    "done": true
  },
  "minecraft:recipes/combat/wooden_sword": {
    "criteria": {
      "has_stick": "2021-12-23 05:14:32 +0000"
    },
    "done": true
  },
  "minecraft:recipes/misc/firework_rocket_simple": {
    "criteria": {
      "has_gunpowder": "2021-12-23 05:27:26 +0000"
    },
    "done": true
  },
  "minecraft:recipes/building_blocks/oak_planks": {
    "criteria": {
      "has_logs": "2021-12-19 23:15:43 +0000"
    },
    "done": true
  },
  "minecraft:recipes/decorations/lime_bed_from_white_bed": {
    "criteria": {
      "has_bed": "2021-12-23 05:13:47 +0000"
    },
    "done": true
  },
  "minecraft:recipes/transportation/dark_oak_boat": {
    "criteria": {
      "in_water": "2021-12-19 23:15:17 +0000"
    },
    "done": true
  },
  "minecraft:recipes/decorations/spruce_fence": {
    "criteria": {
      "has_planks": "2021-12-22 01:12:36 +0000"
    },
    "done": true
  },
  "minecraft:recipes/decorations/glow_item_frame": {
    "criteria": {
      "has_glow_ink_sac": "2021-12-22 01:15:57 +0000"
    },
    "done": true
  },
  "minecraft:recipes/building_blocks/spruce_slab": {
    "criteria": {
      "has_planks": "2021-12-22 01:12:36 +0000"
    },
    "done": true
  },
  "minecraft:adventure/kill_all_mobs": {
    "criteria": {
      "minecraft:spider": "2021-12-19 23:22:02 +0000",
      "minecraft:creeper": "2021-12-23 05:27:25 +0000",
      "minecraft:zombie": "2021-12-19 23:20:18 +0000"
    },
    "done": false
  },
  "minecraft:recipes/decorations/brown_bed_from_white_bed": {
    "criteria": {
      "has_bed": "2021-12-23 05:13:47 +0000"
    },
    "done": true
  },
  "minecraft:recipes/decorations/green_bed_from_white_bed": {
    "criteria": {
      "has_bed": "2021-12-23 05:13:47 +0000"
    },
    "done": true
  },
  "minecraft:recipes/building_blocks/stripped_oak_wood": {
    "criteria": {
      "has_log": "2021-12-23 05:49:40 +0000"
    },
    "done": true
  },
  "minecraft:recipes/building_blocks/brick_slab": {
    "criteria": {
      "has_bricks": "2021-12-22 01:14:20 +0000"
    },
    "done": true
  },
  "minecraft:husbandry/balanced_diet": {
    "criteria": {
      "rotten_flesh": "2021-12-19 23:20:21 +0000",
      "salmon": "2021-12-19 23:17:30 +0000"
    },
    "done": false
  },
  "minecraft:recipes/tools/wooden_hoe": {
    "criteria": {
      "has_stick": "2021-12-23 05:14:32 +0000"
    },
    "done": true
  },
  "minecraft:recipes/decorations/pink_bed_from_white_bed": {
    "criteria": {
      "has_bed": "2021-12-23 05:13:47 +0000"
    },
    "done": true
  },
  "minecraft:recipes/building_blocks/spruce_stairs": {
    "criteria": {
      "has_planks": "2021-12-22 01:12:36 +0000"
    },
    "done": true
  },
  "minecraft:recipes/redstone/spruce_trapdoor": {
    "criteria": {
      "has_planks": "2021-12-22 01:12:36 +0000"
    },
    "done": true
  },
  "minecraft:recipes/misc/bone_meal": {
    "criteria": {
      "has_bone": "2021-12-23 05:38:29 +0000"
    },
    "done": true
  },
  "minecraft:recipes/decorations/brick_wall_from_bricks_stonecutting": {
    "criteria": {
      "has_bricks": "2021-12-22 01:14:20 +0000"
    },
    "done": true
  },
  "minecraft:recipes/building_blocks/brick_slab_from_bricks_stonecutting": {
    "criteria": {
      "has_bricks": "2021-12-22 01:14:20 +0000"
    },
    "done": true
  },
  "minecraft:recipes/decorations/yellow_bed_from_white_bed": {
    "criteria": {
      "has_bed": "2021-12-23 05:13:47 +0000"
    },
    "done": true
  },
  "minecraft:recipes/building_blocks/oak_wood": {
    "criteria": {
      "has_log": "2021-12-19 23:15:43 +0000"
    },
    "done": true
  },
  "minecraft:recipes/food/cooked_salmon": {
    "criteria": {
      "has_salmon": "2021-12-19 23:17:28 +0000"
    },
    "done": true
  },
  "minecraft:recipes/decorations/red_bed_from_white_bed": {
    "criteria": {
      "has_bed": "2021-12-23 05:13:47 +0000"
    },
    "done": true
  },
  "minecraft:recipes/transportation/oak_boat": {
    "criteria": {
      "in_water": "2021-12-19 23:15:17 +0000"
    },
    "done": true
  },
  "minecraft:recipes/decorations/soul_campfire": {
    "criteria": {
      "has_stick": "2021-12-23 05:14:32 +0000"
    },
    "done": true
  },
  "minecraft:recipes/combat/crossbow": {
    "criteria": {
      "has_stick": "2021-12-23 05:14:32 +0000"
    },
    "done": true
  },
  "minecraft:recipes/redstone/spruce_pressure_plate": {
    "criteria": {
      "has_planks": "2021-12-22 01:12:36 +0000"
    },
    "done": true
  },
  "minecraft:recipes/decorations/blue_bed_from_white_bed": {
    "criteria": {
      "has_bed": "2021-12-23 05:13:47 +0000"
    },
    "done": true
  },
  "minecraft:recipes/decorations/light_gray_bed_from_white_bed": {
    "criteria": {
      "has_bed": "2021-12-23 05:13:47 +0000"
    },
    "done": true
  },
  "minecraft:recipes/building_blocks/bone_block": {
    "criteria": {
      "has_bone_meal": "2021-12-23 05:13:16 +0000"
    },
    "done": true
  },
  "DataVersion": 2865
}